[
  { "slovak": "byť prepustený z práce", "english": "be made redundant" },
  { "slovak": "poberať podporu v nezamestnanosti", "english": "be on the dole" },
  { "slovak": "prepustiť", "english": "dismiss" },
  { "slovak": "dať výpoveď", "english": "fire" },
  { "slovak": "dať výpoveď", "english": "give the sack" },
  { "slovak": "odísť zo zamestnania", "english": "give up work" },
  { "slovak": "vstúpiť do štrajku", "english": "go on strike" },
  { "slovak": "bez práce", "english": "jobless" },
  { "slovak": "kto si hľadá prácu", "english": "job seeker" },
  { "slovak": "skončiť prácu", "english": "knock off" },
  { "slovak": "nechať niekoho ísť", "english": "let go" },
  { "slovak": "prepustiť niekoho z práce", "english": "make redundant" },
  { "slovak": "na dovolenke", "english": "on holiday" },
  { "slovak": "nezamestnaný", "english": "out of work" },
  { "slovak": "penzia", "english": "pension" },
  { "slovak": "dôchodca", "english": "pensioner" },
  { "slovak": "poberať štátne dávky", "english": "receive benefits" },
  { "slovak": "rezignovať", "english": "resign" },
  { "slovak": "odísť do dôchodku", "english": "retire" },
  { "slovak": "dôchodok", "english": "retirement" },
  { "slovak": "pracovná dovolenka", "english": "sabbatical" },
  { "slovak": "vyhodiť niekoho z práce", "english": "sack" },
  { "slovak": "pracovná neschopnosť", "english": "sick leave" },
  { "slovak": "vziať si deň voľno", "english": "take a day off" },
  { "slovak": "vziať si voľno", "english": "take time off" },
  { "slovak": "nezamestnaný", "english": "unemployed" },
  { "slovak": "nezamestnanosť", "english": "unemployment" },
  { "slovak": "podpora v nezamestnanosti", "english": "unemployment benefit" }
]
